karmabot/__init__.py
karmabot/__main__.py
karmabot/bot.py
karmabot/commands/add.py
karmabot/commands/age.py
karmabot/commands/control.py
karmabot/commands/doc.py
karmabot/commands/feed.py
karmabot/commands/joke.py
karmabot/commands/note.py
karmabot/commands/score.py
karmabot/commands/template.py
karmabot/commands/tip.py
karmabot/commands/topchannels.py
karmabot/commands/update_username.py
karmabot/commands/welcome.py
karmabot/commands/zen.py
karmabot/db/__all_models.py
karmabot/db/database.py
karmabot/db/karma_note.py
karmabot/db/karma_transaction.py
karmabot/db/karma_user.py
karmabot/db/modelbase.py
karmabot/exceptions.py
karmabot/karma.py
karmabot/main.py
karmabot/settings.py
karmabot/slack.py
karmabot-2.0.1.dist-info/entry_points.txt
karmabot-2.0.1.dist-info/LICENSE
karmabot-2.0.1.dist-info/WHEEL
karmabot-2.0.1.dist-info/METADATA
karmabot-2.0.1.dist-info/RECORD
