Metadata-Version: 2.1
Name: karmabot
Version: 2.0.1
Summary: PyBites Karmabot - A Python based Slack Chatbot for Community interaction
Home-page: https://github.com/PyBites-Open-Source/karmabot
License: MIT
Keywords: karmabot
Author: PyBites
Author-email: info@pybit.es
Maintainer: Patrick-Oliver Groß
Maintainer-email: mail@pogross.de
Requires-Python: >=3.8,<4.0
Classifier: License :: OSI Approved :: MIT License
Classifier: Programming Language :: Python :: 3
Classifier: Programming Language :: Python :: 3 :: Only
Classifier: Programming Language :: Python :: 3.10
Classifier: Programming Language :: Python :: 3.8
Classifier: Programming Language :: Python :: 3.9
Classifier: Topic :: Communications :: Chat
Requires-Dist: SQLAlchemy (>=1.4.20,<2.0.0)
Requires-Dist: feedparser (>=6.0.8,<7.0.0)
Requires-Dist: freezegun (>=1.1.0,<2.0.0)
Requires-Dist: humanize (>=3.10.0,<4.0.0)
Requires-Dist: importlib-metadata (>=3.7.3,<4.0.0)
Requires-Dist: psycopg2-binary (>=2.9.1,<3.0.0)
Requires-Dist: pyjokes (>=0.6.0,<0.7.0)
Requires-Dist: python-dotenv (>=0.18.0,<0.19.0)
Requires-Dist: requests (>=2.25.1,<3.0.0)
Requires-Dist: slack-bolt (>=1.6.1,<2.0.0)
Requires-Dist: slack-sdk (>=3.7.0,<4.0.0)
Project-URL: Repository, https://github.com/PyBites-Open-Source/karmabot
